{
  "annotations": {
    "list": [
      {
        "builtIn": 1,
        "datasource": {
          "type": "datasource",
          "uid": "grafana"
        },
        "enable": true,
        "hide": true,
        "iconColor": "rgba(0, 211, 255, 1)",
        "name": "Annotations & Alerts",
        "target": {
          "limit": 100,
          "matchAny": false,
          "tags": [],
          "type": "dashboard"
        },
        "type": "dashboard"
      }
    ]
  },
  "editable": true,
  "fiscalYearStartMonth": 0,
  "graphTooltip": 0,
  "id": null,
  "links": [],
  "panels": [
    {
      "datasource": {
        "uid": "Tempo"
      },
      "gridPos": {
        "h": 14,
        "w": 24,
        "x": 0,
        "y": 0
      },
      "id": 1,
      "options": {
        "spanStartTimeAlignment": "none"
      },
      "pluginHeight": 0,
      "targets": [],
      "title": "Trace Search",
      "type": "tempo-query"
    }
  ],
  "schemaVersion": 37,
  "style": "dark",
  "tags": [
    "tempo",
    "traces"
  ],
  "templating": {
    "list": []
  },
  "time": {
    "from": "now-6h",
    "to": "now"
  },
  "timepicker": {},
  "timezone": "",
  "title": "Tempo Traces Dashboard - Provisioning",
  "uid": "tempo-traces-provisioned",
  "version": 1,
  "weekStart": ""
}